[
  {
    "id": "istiqadh_alhamdulillah",
    "title": "دعاء الاستيقاظ من النوم",
    "keywords": ["الاستيقاظ من النوم", "دعاء الاستيقاظ", "الحمد لله الذي احيانا", "الصحو من النوم"],
    "text": "الْحَمْدُ لِلَّهِ الَّذِي أَحْيَانَا بَعْدَ مَا أَمَاتَنَا وَإِلَيْهِ النُّشُورُ.",
    "repeat": "مرة واحدة عند الاستيقاظ",
    "reference": "رواه البخاري ومسلم."
  },
  {
    "id": "istiqadh_khawatim_al_imran",
    "title": "قراءة خواتيم سورة آل عمران",
    "keywords": ["خواتيم ال عمران", "ان في خلق السماوات والارض", "اواخر ال عمران"],
    "text": "﴿إِنَّ فِي خَلْقِ السَّمَاوَاتِ وَالْأَرْضِ وَاخْتِلَافِ اللَّيْلِ وَالنَّهَارِ لَآيَاتٍ لِأُولِي الْأَلْبَابِ...﴾ إلى آخر سورة آل عمران.",
    "repeat": "عند الاستيقاظ لقيام الليل",
    "reference": "رواه البخاري ومسلم."
  },
  {
    "id": "istiqadh_dua_taharrus",
    "title": "دعاء من تعارّ من الليل",
    "keywords": ["من تعار من الليل", "الاستيقاظ ليلا", "لا اله الا الله وحده لا شريك له الليل"],
    "text": "لَا إِلَهَ إِلَّا اللَّهُ وَحْدَهُ لَا شَرِيكَ لَهُ، لَهُ الْمُلْكُ وَلَهُ الْحَمْدُ وَهُوَ عَلَى كُلِّ شَيْءٍ قَدِيرٌ، الْحَمْدُ لِلَّهِ، وَسُبْحَانَ اللَّهِ، وَلَا إِلَهَ إِلَّا اللَّهُ، وَاللَّهُ أَكْبَرُ، وَلَا حَوْلَ وَلَا قُوَّةَ إِلَّا بِاللَّهِ. ثُمَّ: رَبِّ اغْفِرْ لِي.",
    "repeat": "من استيقظ ليلًا فقالها ثم دعا استُجيب له",
    "reference": "رواه البخاري.",
    "benefit": "إن دعا استُجيب له، وإن توضّأ وصلّى قُبِلت صلاته."
  }
]
